Workbook

Sheet Executive Dashboard
B2: Sales Forecasting & Revenue Analysis Summary
B4: Total Revenue | E4: Total Profit | H4: Avg Target Achievement | K4: Total Marketing Spend
B5: ='Sales Performance Data'!N122 | E5: ='Sales Performance Data'!P122 | H5: ='Sales Performance Data'!V122 | K5: ='Sales Performance Data'!Q122
B8: Regional Performance Insights Breakdown
B9: Region | C9: Actual Revenue | D9: Sales Target | E9: Achievement %
B10: North America | C10: =SUMIF('Sales Performance Data'!F$2:F$121, "North America", 'Sales Performance Data'!N$2:N$121) | D10: =SUMIF('Sales Performance Data'!F$2:F$121, "North America", 'Sales Performance Data'!U$2:U$121) | E10: =C10/D10
B11: Europe | C11: =SUMIF('Sales Performance Data'!F$2:F$121, "Europe", 'Sales Performance Data'!N$2:N$121) | D11: =SUMIF('Sales Performance Data'!F$2:F$121, "Europe", 'Sales Performance Data'!U$2:U$121) | E11: =C11/D11
B12: Asia-Pacific | C12: =SUMIF('Sales Performance Data'!F$2:F$121, "Asia-Pacific", 'Sales Performance Data'!N$2:N$121) | D12: =SUMIF('Sales Performance Data'!F$2:F$121, "Asia-Pacific", 'Sales Performance Data'!U$2:U$121) | E12: =C12/D12
B13: Latin America | C13: =SUMIF('Sales Performance Data'!F$2:F$121, "Latin America", 'Sales Performance Data'!N$2:N$121) | D13: =SUMIF('Sales Performance Data'!F$2:F$121, "Latin America", 'Sales Performance Data'!U$2:U$121) | E13: =C13/D13

Sheet Sales Performance Data
A1: Order ID | B1: Order Date | C1: Month | D1: Quarter | E1: Year | F1: Region | G1: Country | H1: Customer Segment | I1: Product Category | J1: Product Name | K1: Sales Representative | L1: Units Sold | M1: Unit Price | N1: Revenue | O1: Cost | P1: Profit | Q1: Marketing Spend | R1: Forecasted Revenue | S1: Actual Revenue | T1: Revenue Variance % | U1: Sales Target | V1: Target Achievement % | W1: Season
A2: ORD-2024-1001 | B2: 45292 | C2: January | D2: Q1 | E2: 2024 | F2: Asia-Pacific | G2: Australia | H2: Enterprise | I2: Professional Services | J2: Implementation Blueprint | K2: Sarah Jenkins | L2: 4 | M2: 4778.93 | N2: 19115.72 | O2: 7266.05 | P2: 11849.67 | Q2: 2044.72 | R2: 17686.23 | S2: 19115.72 | T2: 0.0808 | U2: 21813.5 | V2: 0.8763 | W2: Winter
A3: ORD-2024-1002 | B3: 45294 | C3: January | D3: Q1 | E3: 2024 | F3: Latin America | G3: Mexico | H3: Mid-Market | I3: Cloud Software | J3: SaaS Core License | K3: Marcus Vance | L3: 60 | M3: 1187.34 | N3: 71240.4 | O3: 10276.46 | P3: 60963.94 | Q3: 4461.62 | R3: 74084.99 | S3: 71240.4 | T3: -0.0384 | U3: 77382.84 | V3: 0.9206 | W3: Winter
A4: ORD-2024-1003 | B4: 45297 | C4: January | D4: Q1 | E4: 2024 | F4: North America | G4: United States | H4: Mid-Market | I4: Cloud Software | J4: CRM Pro Core | K4: Chloe Bennett | L4: 36 | M4: 1441.01 | N4: 51876.36 | O4: 7760.57 | P4: 44115.79 | Q4: 6900.59 | R4: 51787.24 | S4: 51876.36 | T4: 0.0017 | U4: 53725.41 | V4: 0.9656 | W4: Winter
A5: ORD-2024-1004 | B5: 45300 | C5: January | D5: Q1 | E5: 2024 | F5: Asia-Pacific | G5: Australia | H5: SMB | I5: Cloud Software | J5: Cloud Storage Enterprise | K5: Akiro Tanaka | L5: 12 | M5: 786.85 | N5: 9442.2 | O5: 1431.36 | P5: 8010.84 | Q5: 754.04 | R5: 9649.82 | S5: 9442.2 | T5: -0.0215 | U5: 8600.96 | V5: 1.0978 | W5: Winter
A6: ORD-2024-1005 | B6: 45302 | C6: January | D6: Q1 | E6: 2024 | F6: Asia-Pacific | G6: Japan | H6: Enterprise | I6: Cloud Software | J6: Advanced Analytics Suite | K6: Eleanor Vance | L6: 24 | M6: 2417.42 | N6: 58018.08 | O6: 8958.82 | P6: 49059.26 | Q6: 6162.13 | R6: 63902.98 | S6: 58018.08 | T6: -0.0921 | U6: 67540.91 | V6: 0.859 | W6: Winter
A7: ORD-2024-1006 | B7: 45305 | C7: January | D7: Q1 | E7: 2024 | F7: Latin America | G7: Brazil | H7: Enterprise | I7: Hardware & Infrastructure | J7: Enterprise Server V4 | K7: Marcus Vance | L7: 4 | M7: 8624.82 | N7: 34499.28 | O7: 18228.33 | P7: 16270.95 | Q7: 2526.76 | R7: 33509.65 | S7: 34499.28 | T7: 0.0295 | U7: 28221.8 | V7: 1.2224 | W7: Winter
A8: ORD-2024-1007 | B8: 45308 | C8: January | D8: Q1 | E8: 2024 | F8: North America | G8: Canada | H8: Enterprise | I8: Hardware & Infrastructure | J8: Quantum Workstation | K8: Marcus Vance | L8: 4 | M8: 4449.72 | N8: 17798.88 | O8: 10132.72 | P8: 7666.16 | Q8: 1116.17 | R8: 19245.46 | S8: 17798.88 | T8: -0.0752 | U8: 15018.46 | V8: 1.1851 | W8: Winter
A9: ORD-2024-1008 | B9: 45310 | C9: January | D9: Q1 | E9: 2024 | F9: North America | G9: Canada | H9: Enterprise | I9: Hardware & Infrastructure | J9: Secure Route Switch | K9: Akiro Tanaka | L9: 12 | M9: 1167.53 | N9: 14010.36 | O9: 7895.24 | P9: 6115.12 | Q9: 1189.73 | R9: 13682.67 | S9: 14010.36 | T9: 0.0239 | U9: 13403.04 | V9: 1.0453 | W9: Winter
A10: ORD-2024-1009 | B10: 45313 | C10: January | D10: Q1 | E10: 2024 | F10: Asia-Pacific | G10: Australia | H10: Mid-Market | I10: Cybersecurity | J10: Endpoint Detection X | K10: Eleanor Vance | L10: 75 | M10: 1074.25 | N10: 80568.75 | O10: 15966.34 | P10: 64602.41 | Q10: 9864.81 | R10: 77036.73 | S10: 80568.75 | T10: 0.0458 | U10: 68465.31 | V10: 1.1768 | W10: Winter
A11: ORD-2024-1010 | B11: 45316 | C11: January | D11: Q1 | E11: 2024 | F11: Europe | G11: United Kingdom | H11: Mid-Market | I11: Professional Services | J11: Cloud Migration Consulting | K11: Sofia Rodriguez | L11: 2 | M11: 7395.26 | N11: 14790.52 | O11: 6172.34 | P11: 8618.18 | Q11: 1215.88 | R11: 16825.52 | S11: 14790.52 | T11: -0.1209 | U11: 17490.77 | V11: 0.8456 | W11: Winter
A12: ORD-2024-1011 | B12: 45319 | C12: January | D12: Q1 | E12: 2024 | F12: Asia-Pacific | G12: Australia | H12: Enterprise | I12: Cloud Software | J12: Cloud Storage Enterprise | K12: David Kim | L12: 24 | M12: 780.8 | N12: 18739.2 | O12: 2948.87 | P12: 15790.33 | Q12: 1454.31 | R12: 16964.81 | S12: 18739.2 | T12: 0.1046 | U12: 20972.83 | V12: 0.8935 | W12: Winter
A13: ORD-2024-1012 | B13: 45321 | C13: January | D13: Q1 | E13: 2024 | F13: Asia-Pacific | G13: India | H13: Enterprise | I13: Cloud Software | J13: SaaS Core License | K13: Chloe Bennett | L13: 48 | M13: 1194.39 | N13: 57330.72 | O13: 8345.92 | P13: 48984.8 | Q13: 4415.29 | R13: 50284.84 | S13: 57330.72 | T13: 0.1401 | U13: 51803.64 | V13: 1.1067 | W13: Winter
... A121: ORD-2026-1120 | B121: 45613 | C121: November | D121: Q4 | E121: 2024 | F121: North America | G121: United States | H121: Mid-Market | I121: Cloud Software | J121: Cloud Storage Enterprise | K121: James O'Connor | L121: 60 | M121: 770.3 | N121: 46218 | O121: 7222.8 | P121: 38995.2 | Q121: 5480.29 | R121: 43403.36 | S121: 46218 | T121: 0.0648 | U121: 40050.26 | V121: 1.154 | W121: Autumn
A122: Total / Average | L122: =SUM(L2:L121) | N122: =SUM(N2:N121) | O122: =SUM(O2:O121) | P122: =SUM(P2:P121) | Q122: =SUM(Q2:Q121) | R122: =SUM(R2:R121) | S122: =SUM(S2:S121) | T122: =(S122-R122)/R122 | U122: =SUM(U2:U121) | V122: =S122/U122
